{
  "_class": "group",
  "do_objectID": "35DD6EFD-82B8-4C33-A7CF-59F64DC3DA25",
  "exportOptions": {
    "_class": "exportOptions",
    "exportFormats": [
    ],
    "includedLayerIds": [
    ],
    "layerOptions": 0,
    "shouldTrim": false
  },
  "frame": {
    "_class": "rect",
    "constrainProportions": false,
    "height": 89,
    "width": 306,
    "x": 93,
    "y": 83
  },
  "hasClickThrough": false,
  "isFlippedHorizontal": false,
  "isFlippedVertical": false,
  "isLocked": false,
  "isVisible": true,
  "layerListExpandedType": 0,
  "layers": [
    {
      "class": "shapeGroup",
      "id": "5C9B69FF-1A14-42FE-A161-3825B1670F98"
    },
    {
      "class": "text",
      "id": "AE0220B7-660F-479F-9FD9-03AFFC7981C2"
    }
  ],
  "name": "textfield / Classic / TextField Shadow",
  "nameIsFixed": true,
  "resizingConstraint": 63,
  "resizingType": 0,
  "rotation": 0,
  "shouldBreakMaskChain": false,
  "style": {
    "_class": "style",
    "endDecorationType": 0,
    "miterLimit": 10,
    "startDecorationType": 0
  },
  "userInfo": {
    "com.animaapp.stc-sketch-plugin": {
      "kModelPropertiesKey": {
      }
    }
  }
}