{
  "_class": "shapeGroup",
  "clippingMaskMode": 0,
  "do_objectID": "F985757C-CC2B-4A7D-A277-D638C33CEA38",
  "exportOptions": {
    "_class": "exportOptions",
    "exportFormats": [
    ],
    "includedLayerIds": [
    ],
    "layerOptions": 0,
    "shouldTrim": false
  },
  "frame": {
    "_class": "rect",
    "constrainProportions": true,
    "height": 85,
    "width": 85,
    "x": 9,
    "y": 9
  },
  "hasClickThrough": false,
  "hasClippingMask": false,
  "isFlippedHorizontal": false,
  "isFlippedVertical": false,
  "isLocked": false,
  "isVisible": true,
  "layerListExpandedType": 1,
  "layers": [
    {
      "class": "oval",
      "id": "0C9EDA16-8BED-4CC7-8977-F1E25D09C5FD"
    }
  ],
  "name": "Oval Copy 8",
  "nameIsFixed": false,
  "resizingConstraint": 63,
  "resizingType": 0,
  "rotation": 0,
  "shouldBreakMaskChain": false,
  "style": {
    "_class": "style",
    "blur": {
      "_class": "blur",
      "center": "{0.5, 0.5}",
      "isEnabled": false,
      "motionAngle": 0,
      "radius": 7.999999523162842,
      "type": 0
    },
    "borders": [
      {
        "_class": "border",
        "color": {
          "_class": "color",
          "alpha": 1,
          "blue": 0.8352941176,
          "green": 0.7921568627,
          "red": 0.7294117647
        },
        "fillType": 0,
        "isEnabled": false,
        "position": 1,
        "thickness": 0.7999999523162842
      }
    ],
    "do_objectID": "E0389062-00DF-4E65-A7D3-9EF290550FC3",
    "endDecorationType": 0,
    "fills": [
      {
        "_class": "fill",
        "color": {
          "_class": "color",
          "alpha": 1,
          "blue": 0.8862745098039215,
          "green": 0.8509803921568627,
          "red": 0.8431372549019608
        },
        "fillType": 0,
        "isEnabled": true,
        "noiseIndex": 0,
        "noiseIntensity": 0,
        "patternFillType": 0,
        "patternTileScale": 1
      }
    ],
    "miterLimit": 10,
    "sharedObjectID": "60454EBC-2C3E-44E2-8008-B888477DCD64",
    "startDecorationType": 0
  },
  "windingRule": 1
}