{
  "_class": "shapeGroup",
  "clippingMaskMode": 0,
  "do_objectID": "B8DDF5FB-3F35-4C77-9AAA-CCBD9B3FAC9F",
  "exportOptions": {
    "_class": "exportOptions",
    "exportFormats": [
    ],
    "includedLayerIds": [
    ],
    "layerOptions": 0,
    "shouldTrim": false
  },
  "frame": {
    "_class": "rect",
    "constrainProportions": false,
    "height": 60,
    "width": 306,
    "x": 0,
    "y": 29
  },
  "hasClickThrough": false,
  "hasClippingMask": false,
  "isFlippedHorizontal": false,
  "isFlippedVertical": false,
  "isLocked": false,
  "isVisible": true,
  "layerListExpandedType": 1,
  "layers": [
    {
      "class": "rectangle",
      "id": "4C623284-404E-4E1F-A9A9-81C358342DB9"
    }
  ],
  "name": "Rectangle 2 Copy 11",
  "nameIsFixed": false,
  "resizingConstraint": 63,
  "resizingType": 0,
  "rotation": 0,
  "shouldBreakMaskChain": false,
  "style": {
    "sharedObjectID": "583A7629-2D16-48F7-BC5D-4656DAB8F484"
  },
  "userInfo": {
    "com.animaapp.stc-sketch-plugin": {
      "kModelPropertiesKey": {
      }
    }
  },
  "windingRule": 1
}