{
  "_class": "artboard",
  "backgroundColor": {
    "_class": "color",
    "alpha": 1,
    "blue": 1,
    "green": 1,
    "red": 1
  },
  "do_objectID": "0F8CF006-B346-4761-811D-0116804A3878",
  "exportOptions": {
    "_class": "exportOptions",
    "exportFormats": [
    ],
    "includedLayerIds": [
    ],
    "layerOptions": 0,
    "shouldTrim": false
  },
  "frame": {
    "_class": "rect",
    "constrainProportions": false,
    "height": 584,
    "width": 1886,
    "x": -237,
    "y": 1393
  },
  "hasBackgroundColor": false,
  "hasClickThrough": true,
  "horizontalRulerData": {
    "_class": "rulerData",
    "base": 0,
    "guides": [
    ]
  },
  "includeBackgroundColorInExport": true,
  "includeInCloudUpload": true,
  "isFlippedHorizontal": false,
  "isFlippedVertical": false,
  "isLocked": false,
  "isVisible": true,
  "layerListExpandedType": 2,
  "layers": [
    {
      "class": "shapeGroup",
      "id": "E95828E7-33D2-4B68-8FD7-F86645669CC3"
    },
    {
      "class": "shapeGroup",
      "id": "37113B3C-E628-43B0-9DD3-118DBFE8350C"
    },
    {
      "class": "shapeGroup",
      "id": "FF513FB0-EBE6-4F5F-8704-743DE069C5A5"
    },
    {
      "class": "shapeGroup",
      "id": "A06AF504-63E5-458B-BFA0-592FA93DB336"
    },
    {
      "class": "text",
      "id": "77C5E280-036E-421D-A699-B348D90A51DB"
    },
    {
      "class": "text",
      "id": "12347FF3-EB74-4C02-B1FF-731FA47FA700"
    },
    {
      "class": "text",
      "id": "EB11F077-5EEA-43F3-939D-24CAFB991D62"
    },
    {
      "class": "text",
      "id": "09C0E778-2CD7-4B10-9355-3A18E70E7BE3"
    },
    {
      "class": "text",
      "id": "AD0F89BA-D8B1-4F50-852D-93D77746B549"
    },
    {
      "class": "text",
      "id": "5C670744-3409-498B-9882-5E5C55586968"
    },
    {
      "class": "text",
      "id": "F4EBB58F-50B3-4D29-96B5-D90F4C1C9C90"
    },
    {
      "class": "text",
      "id": "39302FB4-3B75-4A8D-B7B0-D1A7E460E5A3"
    },
    {
      "class": "text",
      "id": "5F57C465-679C-497D-890B-E3F4F0190B95"
    },
    {
      "class": "text",
      "id": "91437522-9FEB-4B0D-9740-1F0F20E0F997"
    },
    {
      "class": "text",
      "id": "4A11D024-BAE0-4C4D-9258-9C98B0453CAC"
    },
    {
      "class": "text",
      "id": "8C659272-268E-46EA-A51D-5D18C9C56046"
    },
    {
      "class": "symbolInstance",
      "id": "C4E22518-93BE-4C18-8176-CE929B22BAB9"
    },
    {
      "class": "shapeGroup",
      "id": "6B58CE23-B215-4942-8DC0-94E3BB36FD21"
    },
    {
      "class": "symbolInstance",
      "id": "29AC8C2C-E3FB-4366-8B60-6836C3849DD1"
    },
    {
      "class": "shapeGroup",
      "id": "C4F8DA52-67ED-466C-BE56-1B8F938BFA61"
    },
    {
      "class": "symbolInstance",
      "id": "57766E8D-77FD-454C-BA37-9360F28F35A3"
    },
    {
      "class": "shapeGroup",
      "id": "89A7268C-F223-410C-97E3-7079D228520D"
    },
    {
      "class": "symbolInstance",
      "id": "57BACA2A-7FCC-4F7B-9D8E-CC34649E8338"
    },
    {
      "class": "shapeGroup",
      "id": "C162FEB0-69EE-4429-81C8-1AC0D3E6F67D"
    }
  ],
  "name": "Select Dropdown",
  "nameIsFixed": true,
  "resizesContent": false,
  "resizingConstraint": 63,
  "resizingType": 0,
  "rotation": 0,
  "shouldBreakMaskChain": false,
  "style": {
    "_class": "style",
    "endDecorationType": 0,
    "miterLimit": 10,
    "startDecorationType": 0
  },
  "userInfo": {
    "com.animaapp.stc-sketch-plugin": {
      "kModelPropertiesKey": {
      }
    }
  },
  "verticalRulerData": {
    "_class": "rulerData",
    "base": 0,
    "guides": [
    ]
  }
}